LICENSE
README.rst
setup.py
asyncnt/__init__.py
asyncnt.egg-info/PKG-INFO
asyncnt.egg-info/SOURCES.txt
asyncnt.egg-info/dependency_links.txt
asyncnt.egg-info/requires.txt
asyncnt.egg-info/top_level.txt