Metadata-Version: 1.2
Name: asyncnt
Version: 1.7.0
Summary: An asynchronous way to fetch data from nitrotype.
Home-page: https://github.com/axemalt/asyncnt
Author: axemalt
License: MIT
Platform: UNKNOWN
Classifier: Programming Language :: Python :: 3
Classifier: License :: OSI Approved :: MIT License
Classifier: Operating System :: OS Independent
Requires-Python: >=3.7.0
